{
  "id": "sprint_判断冲刺_2",
  "title": "判断冲刺2",
  "subject": "全科",
  "type": "judge",
  "count": 30,
  "questions": [
    {
      "id": 1,
      "type": "judge",
      "q": "证券公司开展柜台交易业务中，需要向投资者收取履约保证金的，保证金应存入在证券公司与投资者双方约定的金融机构开立的专门账户。（）",
      "c": {
        "A": "错",
        "B": "对"
      },
      "a": "B",
      "an": "证券公司与投资者约定抵押、质押等财产担保的，应当依法办理担保设定手续；向投资者收取履约保证金的，应当在双方约定的金融机构开立专门账户存放，不得违约动用。",
      "subject": "法律法规"
    },
    {
      "id": 2,
      "type": "judge",
      "q": "公司按股东的持股比例向原股东分配公司的新股认购权，准其优先认购新股的方式，按老股一般配售若干新股，以保护原股东的权益及其对公司控制权的是定向增发。（）",
      "c": {
        "A": "错",
        "B": "对"
      },
      "a": "A",
      "an": "【配股】是公司按股东的持股比例向原股东分配公司的新股认购权，准其优先认购股份的方式。即按老股一股配售若干新股，以保护原股东的权益及其对公司的控制权。",
      "subject": "金融基础"
    },
    {
      "id": 3,
      "type": "judge",
      "q": "证券公司受期货公司委托从事中间介绍业务，应当提供协助客户办理开户手续、代理客户进行期货交易、提供期货行情信息、交易设施等服务。（）",
      "c": {
        "A": "错",
        "B": "对"
      },
      "a": "A",
      "an": "证券公司受期货公司委托从事介绍业务，应当提供下列服务：（1）协助办理开户手续；（2）提供期货行情信息、交易设施；（3）中国证监会规定的其他服务。证券公司不得代理客户进行期货交易、结算或者交割，不得代期货公司、客户收付期货保证金，不得利用证券资金账户为客户存取、划转期货保证金。",
      "subject": "法律法规"
    },
    {
      "id": 4,
      "type": "judge",
      "q": "根据《证券期货经营机构私募资产管理业务管理办法》，违反法律、行政法规和相关规定，情节严重，中国证监会可以对证券公司相关从业人员依法采取市场禁入措施。（）",
      "c": {
        "A": "错",
        "B": "对"
      },
      "a": "B",
      "an": "【证券公司、托管人、销售机构和投资顾问】等服务机构的相关从业人员违反法律、行政法规和相关规定，情节严重的，中国证监会可以依法采取市场禁入措施。",
      "subject": "法律法规"
    },
    {
      "id": 5,
      "type": "judge",
      "q": "根据《期货交易管理条例》，申请设立期货公司，主要股东及实际控制人最近2年无重大违法违规记录。（）",
      "c": {
        "A": "错",
        "B": "对"
      },
      "a": "A",
      "an": "申请设立期货公司，应当符合《公司法》的规定（包括：有符合法律、行政法规规定的公司章程），并具备下列条件：1、注册资本最低限额为人民币1亿元；2、董事、监事、高级管理人员具备任职条件，从业人员具有期货从业资格；3、有符合法律、行政法规规定的公司章程；4、主要股东以及实际控制人具有持续盈利能力，信誉良好，最近【3年】无重大违法违规记录；5、有合格的经营场所和业务设施；6、有健全的风险管理和内部控制制度；7、国务院期货监督管理机构规定的其他条件。",
      "subject": "法律法规"
    },
    {
      "id": 6,
      "type": "judge",
      "q": "公司享有法人财产权，应对公司债务承担有限清偿责任。（）",
      "c": {
        "A": "错",
        "B": "对"
      },
      "a": "B",
      "an": "公司是企业法人，有独立的法人财产，享有法人财产权。公司以其全部财产为限对公司的债务承担责任。",
      "subject": "法律法规"
    },
    {
      "id": 7,
      "type": "judge",
      "q": "下列不属于证券公司融资渠道的是向客户拆借。（）",
      "c": {
        "A": "错",
        "B": "对"
      },
      "a": "B",
      "an": "证券公司应建立并完善融资策略，提高融资来源的多元化和稳定程度，建立包括但不限于银行借款、同业拆借、债券、收益凭证、短期融资券、证券回购等灵活的场内及场外融资渠道。",
      "subject": "法律法规"
    },
    {
      "id": 8,
      "type": "judge",
      "q": "强制减仓制度是指交易所将当日以涨跌停板价格申报的未成交平仓报单，以当日涨跌停板价格与该合约净持仓盈利客户按照持仓比例自动撮合成交。（）",
      "c": {
        "A": "错",
        "B": "对"
      },
      "a": "B",
      "an": "【强制减仓制度】是指交易所将当日以涨跌停板价格申报的未成交平仓报单，以当日涨跌停板价格与该合约净持仓盈利客户按照持仓比例自动撮合成交。",
      "subject": "金融基础"
    },
    {
      "id": 9,
      "type": "judge",
      "q": "证券公司金融衍生品备案和后续监测管理由中国证监会负责。（）",
      "c": {
        "A": "错",
        "B": "对"
      },
      "a": "A",
      "an": "中证机构间报价系统股份有限公司负责对证券公司金融衍生品备案和后续监测管理。",
      "subject": "法律法规"
    },
    {
      "id": 10,
      "type": "judge",
      "q": "个别合伙因重大过失造成企业债务的，应当以其在合伙企业中的财产份额为限承担责任。（）",
      "c": {
        "A": "错",
        "B": "对"
      },
      "a": "A",
      "an": "1个合伙人或者数个合伙人在执业活动中因故意或者重大过失造成合伙企业债务的，应当承担无限责任或者无限连带责任，其他合伙人以其在合伙企业中的财产份额为限承担责任。合伙人在执业活动中非因故意或者重大过失造成的合伙企业债务以及合伙企业的其他债务，由全体合伙人承担无限连带责任。合伙人执业活动中因故意或者重大过失造成的合伙企业债务，以合伙企业财产对外承担责任后，该合伙人应当按照合伙协议的约定对合伙企业造成的损失承担赔偿责任。",
      "subject": "法律法规"
    },
    {
      "id": 11,
      "type": "judge",
      "q": "首次公开发行股票，网上投资者有效申购倍数超过150倍的，回拨后网下发行比例不超过本次公开发行股票数量的20%。（）",
      "c": {
        "A": "错",
        "B": "对"
      },
      "a": "A",
      "an": "网上资者有效申购倍数超过150倍的，回拨后网下发行比例不超过本次公开发行股票数量的10%。",
      "subject": "金融基础"
    },
    {
      "id": 12,
      "type": "judge",
      "q": "合格境内机构投资者，是指经一国金融管理当局审批通过、获准直接投资境外股票或者债券市场的国内机构投资者，在一定规定下通过基金形式募集一定额度的人民币资金。（）",
      "c": {
        "A": "错",
        "B": "对"
      },
      "a": "B",
      "an": "合格境内机构投资者，是指经一国金融管理当局审批通过、获准直接投资境外股票或者债券市场的国内机构投资者，在一定规定下通过【基金】形式募集一定额度的人民币资金。",
      "subject": "金融基础"
    },
    {
      "id": 13,
      "type": "judge",
      "q": "甲公司公开发行股票5亿股，有效报价投资者的数量最少为10家。（）",
      "c": {
        "A": "错",
        "B": "对"
      },
      "a": "A",
      "an": "公开发行股票数量在4亿股（含）以下的，有效报价投资者的数量不少于10家；公开发行股票数量在【4亿股以上】的，有效报价投资者的数量不少于20家。",
      "subject": "金融基础"
    },
    {
      "id": 14,
      "type": "judge",
      "q": "收购人或者收购人的控股股东，利用上市公司收购，损害被收购公司及其股东的合法权益的，应责令改正，给予通报批评；情节严重的，并处以罚款。（）",
      "c": {
        "A": "错",
        "B": "对"
      },
      "a": "A",
      "an": "收购人或者收购人的控股股东，利用上市公司收购，损害被收购公司及其股东的合法权益的，责令改正，给予警告；情节严重的，并处以十万元以上六十万元以下的罚款。给被收购公司及其股东造成损失的，依法承担赔偿责任。对直接负责的主管人员和其他直接责任人员给予警告，并处以三万元以上三十万元以下的罚款。",
      "subject": "法律法规"
    },
    {
      "id": 15,
      "type": "judge",
      "q": "操纵证券、期货市场，持有证券的流通股份数达到该证券实际流通股份总量30%以上，且在该证券连续20个交易日内连续买卖股份数累计达到该证券同期总成交量30%以上的，应予立案追诉。（）",
      "c": {
        "A": "错",
        "B": "对"
      },
      "a": "A",
      "an": "持有或者实际控制证券的流通股份数量达到该证券的实际流通股份总量10%以上，实施刑法第一百八十二条第一款第一项操纵证券市场行为，连续10个交易日的累计成交量达到同期该证券总成交量20%以上的应予立案追诉。",
      "subject": "法律法规"
    },
    {
      "id": 16,
      "type": "judge",
      "q": "沪深300指数是中国证券市场中历史最悠久、数据最完整的成分股指数。（）",
      "c": {
        "A": "错",
        "B": "对"
      },
      "a": "A",
      "an": "【深证成分指数】是中国证券市场中历史最悠久、数据最完整的成分股指数。",
      "subject": "金融基础"
    },
    {
      "id": 17,
      "type": "judge",
      "q": "根据《关于加强证券经纪业务管理的规定》，证券公司技术人员可以从事客户账户及客户资金存管业务活动。（）",
      "c": {
        "A": "错",
        "B": "对"
      },
      "a": "A",
      "an": "根据《关于加强证券经纪业务管理的规定》，从事【技术】、风险监控、合规管理的人员不得从事营销、客户账户及客户资金存管等业务活动。",
      "subject": "法律法规"
    },
    {
      "id": 18,
      "type": "judge",
      "q": "对证券公司投资银行类项目负有主要管理或执行责任人员的收入递延支付年限，原则上不得少于3年。（）",
      "c": {
        "A": "错",
        "B": "对"
      },
      "a": "B",
      "an": "应当针对管理和执行投资银行类项目的主要人员建立收入递延支付机制，合理确定收入递延支付标准，明确递延支付人员范围、递延支付年限和比例等内容。对投资银行类项目负有主要管理或执行责任人员的收入递延支付年限原则上不得少于3年。",
      "subject": "法律法规"
    },
    {
      "id": 19,
      "type": "judge",
      "q": "证券公司风险管理部门应当向董事会提交风险管理日报、月报、年报等定期报告。（）",
      "c": {
        "A": "错",
        "B": "对"
      },
      "a": "A",
      "an": "风险管理部门应当向【经理层】提交风险管理日报、月报、年报等定期报告，反映风险识别、评估结果和应对方案，对重大风险应提供专项评估报告，确保经理层及时、充分了解公司风险状况。",
      "subject": "法律法规"
    },
    {
      "id": 20,
      "type": "judge",
      "q": "地方政府债券按资金用途和偿还资金来源不同可以分为普通债券、特种债券。（）",
      "c": {
        "A": "错",
        "B": "对"
      },
      "a": "A",
      "an": "地方政府债券按资金用途和偿还资金来源不同，通常可以分为一般债券（普通债券）和专项债券（收入债券）。",
      "subject": "金融基础"
    },
    {
      "id": 21,
      "type": "judge",
      "q": "证券评级机构的董事、监事和高级管理人员以及评级从业人员可以在受评级机构或者受评级证券发行人兼职。（）",
      "c": {
        "A": "错",
        "B": "对"
      },
      "a": "A",
      "an": "证券评级机构的董事、监事和高级管理人员以及评级从业人员【不得】在受评级机构或者受评级证券发行人兼职。",
      "subject": "法律法规"
    },
    {
      "id": 22,
      "type": "judge",
      "q": "根据《证券公司和证券投资基金管理公司合规管理办法》，证券公司开展各项业务，关联交易管理方面，坚决防止关联交易和利益输送。（）",
      "c": {
        "A": "错",
        "B": "对"
      },
      "a": "A",
      "an": "可以进行关联交易，需要完善保障关联交易公允性和合规性的制度。",
      "subject": "法律法规"
    },
    {
      "id": 23,
      "type": "judge",
      "q": "单只转融通标的证券转融券余额达到该证券上市可流通市值的10%时，暂停该证券的转融券业务，并向市场公布。（）",
      "c": {
        "A": "错",
        "B": "对"
      },
      "a": "B",
      "an": "单只转融通标的证券转融券余额达到该证券上市可流通市值的10%时，暂停该证券的转融券业务，并向市场公布。",
      "subject": "法律法规"
    },
    {
      "id": 24,
      "type": "judge",
      "q": "根据《证券公司全面风险管理规范》，对证券公司全面风险管理情况进行自律管理的是中国证券业协会。（）",
      "c": {
        "A": "错",
        "B": "对"
      },
      "a": "B",
      "an": "中国证券业协会可以对证券公司全面风险管理情况进行自律管理，证券公司应予以配合。",
      "subject": "法律法规"
    },
    {
      "id": 25,
      "type": "judge",
      "q": "资产管理计划运作期间，证券资产管理业务信息披露为投资非标准化资产的资产管理计划至少每月披露一次净值，每年度结束之日起3个月内披露年度报告。（）",
      "c": {
        "A": "错",
        "B": "对"
      },
      "a": "A",
      "an": "资产管理计划运作期间，证券期货经营机构应当按照以下要求向投资者提供相关信息：1、投资标准化资产的资产管理计划至少每周披露一次净值，投资非标准化资产的资产管理计划至少【每季度】披露一次净值。2、开放式资产管理计划净值的披露频率不得低于资产管理计划的开放频率，分级资产管理计划应当披露各类别份额净值。3、每季度结束之日起1个月内披露季度报告，每年度结束之日起【4个月内】披露年度报告。4、发生资产管理合同约定的或者可能影响投资者利益的重大事项时，在事项发生之日起5日内向投资者披露。5、中国证监会规定的其他要求。资产管理计划成立不足3个月或者存续期间不足3个月的，证券公司可以不编制资产管理计划当期的季度报告和年度报告。",
      "subject": "法律法规"
    },
    {
      "id": 26,
      "type": "judge",
      "q": "核准制是证券监管机构对申报文件的真实性、准确性、完整性和及时性做合规性的形式审查，而将发行人的质量留给证券中介机构来判断和决定的股票发行监管制度。（）",
      "c": {
        "A": "错",
        "B": "对"
      },
      "a": "A",
      "an": "【注册制】的特点是证券监管机构对申报文件的真实性、准确性、完整性和及时性做合规性的形式审查，而将发行人的质量留给证券中介机构来判断和决定。",
      "subject": "金融基础"
    },
    {
      "id": 27,
      "type": "judge",
      "q": "根据行业协会相关规则规定，以地方政府为直接或间接债务人的基础资产，属于资产证券化基础资产负面清单范畴，但地方政府按照事先公开的收益约定规则，在政府与社会资本合作模式（PPP）下应当支付或承担的财政补贴除外。（）",
      "c": {
        "A": "错",
        "B": "对"
      },
      "a": "B",
      "an": "以地方政府为直接或间接债务人的基础资产，属于资产证券化基础资产负面清单。但地方政府按照事先公开的收益约定规则，在政府与社会资本合作模式（PPP）下应当支付或承担的财政补贴除外。",
      "subject": "法律法规"
    },
    {
      "id": 28,
      "type": "judge",
      "q": "私募基金子公司及其下设基金管理机构将自有资金投资于本机构设立的私募基金的，对单只基金的投资金额不得超过该只基金总额的20%。（）",
      "c": {
        "A": "错",
        "B": "对"
      },
      "a": "B",
      "an": "私募基金子公司及其下设基金管理机构将自有资金投资于本机构设立的私募基金的，对单只基金的投资金额不得超过该只基金总额的【20%】。",
      "subject": "金融基础"
    },
    {
      "id": 29,
      "type": "judge",
      "q": "资金需求者与资金初始供应者之间不发生直接信贷关系，而是由金融中介机构起桥梁作用，两者只与金融机构发生债权债务关系。这反映了间接融资的融资的相对集中性特点。（）",
      "c": {
        "A": "错",
        "B": "对"
      },
      "a": "A",
      "an": "资金需求者与资金初始供应者之间不发生直接信贷关系，而是由金融中介机构起桥梁作用，二者只与金融机构发生债权债务关系。这反映了间接融资的资金获得的【间接性】特点&amp;nbsp;&amp;nbsp;。",
      "subject": "金融基础"
    },
    {
      "id": 30,
      "type": "judge",
      "q": "截至2017年末，全球第一大黑色金属期货市场和第二大有色金属期货市场的是纽约期货交易所。（）",
      "c": {
        "A": "错",
        "B": "对"
      },
      "a": "A",
      "an": "截至2017年末，上海期货交易所成为全球第一大黑色金属期货市场和第二大有色金属期货市场。",
      "subject": "金融基础"
    }
  ]
}